ophelian/README.md
ophelian/__init__.py
ophelian/_info.py
ophelian/_logger.py
ophelian/ophelian_spark/__init__.py
ophelian/ophelian_spark/_wrapper.py
ophelian/ophelian_spark/evaluation/__init__.py
ophelian/ophelian_spark/evaluation/features.py
ophelian/ophelian_spark/evaluation/metrics.py
ophelian/ophelian_spark/functions.py
ophelian/ophelian_spark/generic.py
ophelian/ophelian_spark/ml/__init__.py
ophelian/ophelian_spark/ml/feature_miner.py
ophelian/ophelian_spark/ml/graphs/__init__.py
ophelian/ophelian_spark/ml/optim/__init__.py
ophelian/ophelian_spark/ml/optim/utils.py
ophelian/ophelian_spark/ml/sampling/__init__.py
ophelian/ophelian_spark/ml/sampling/synthetic_sample.py
ophelian/ophelian_spark/ml/supervised/__init__.py
ophelian/ophelian_spark/ml/supervised/classification.py
ophelian/ophelian_spark/ml/supervised/regression.py
ophelian/ophelian_spark/ml/unsupervised/__init__.py
ophelian/ophelian_spark/ml/unsupervised/cluster.py
ophelian/ophelian_spark/ml/unsupervised/feature.py
ophelian/ophelian_spark/read/__init__.py
ophelian/ophelian_spark/read/spark_read.py
ophelian/ophelian_spark/session/__init__.py
ophelian/ophelian_spark/session/spark.py
ophelian/ophelian_spark/streaming/__init__.py
ophelian/ophelian_spark/streaming/streaming_process.py
ophelian/ophelian_spark/write/__init__.py
ophelian/ophelian_spark/write/spark_write.py
ophelian/start.py
ophelian-0.1.4.dist-info/LICENSE
ophelian-0.1.4.dist-info/METADATA
ophelian-0.1.4.dist-info/WHEEL
ophelian-0.1.4.dist-info/RECORD
